aliyunsdksnsuapi/__init__.py
aliyunsdksnsuapi/endpoint.py
aliyunsdksnsuapi/request/__init__.py
aliyunsdksnsuapi/request/v20180709/BandOfferOrderRequest.py
aliyunsdksnsuapi/request/v20180709/BandPrecheckRequest.py
aliyunsdksnsuapi/request/v20180709/BandStartSpeedUpRequest.py
aliyunsdksnsuapi/request/v20180709/BandStatusQueryRequest.py
aliyunsdksnsuapi/request/v20180709/BandStopSpeedUpRequest.py
aliyunsdksnsuapi/request/v20180709/MobileStartSpeedUpRequest.py
aliyunsdksnsuapi/request/v20180709/MobileStatusQueryRequest.py
aliyunsdksnsuapi/request/v20180709/MobileStopSpeedUpRequest.py
aliyunsdksnsuapi/request/v20180709/__init__.py
aliyun_python_sdk_snsuapi-1.0.0.dist-info/LICENSE
aliyun_python_sdk_snsuapi-1.0.0.dist-info/METADATA
aliyun_python_sdk_snsuapi-1.0.0.dist-info/WHEEL
aliyun_python_sdk_snsuapi-1.0.0.dist-info/top_level.txt
aliyun_python_sdk_snsuapi-1.0.0.dist-info/RECORD
